{
  "strategy": "mean_reversion",
  "market": "sp500",
  "params": {
    "rsi_period": 14,
    "rsi_oversold": 52,
    "zscore_lookback": 38,
    "zscore_entry": -1.8,
    "atr_period": 20,
    "atr_stop_mult": 1.35,
    "profit_target_atr_mult": 2.5,
    "max_hold_days": 20,
    "sma200_filter": false,
    "ibs_max": 0.7,
    "volume": {
      "lookback": 20,
      "min_ratio": 0.5,
      "surge_threshold": 1.5,
      "surge_boost": 0.0,
      "dry_penalty": 0.0
    },
    "earnings_blackout": {
      "enabled": true,
      "days_before": 5,
      "days_after": 1
    },
    "breadth": {
      "enabled": true,
      "metric": "pct_above_50ma",
      "low_threshold": 48.0,
      "high_threshold": 58.0,
      "low_boost": 0.015,
      "high_penalty": 0.015
    },
    "relative_strength": {
      "enabled": false
    },
    "cointegration_filter": {
      "enabled": false
    }
  },
  "metrics": {
    "total_trades": 617,
    "cagr_pct": 11.5805,
    "cagr_full_period_pct": 9.7417,
    "sharpe": 0.4725,
    "sortino": 0.6029,
    "max_drawdown_pct": 21.3179,
    "win_rate_pct": 39.55,
    "profit_factor": 1.2861,
    "total_pnl": 4734.11,
    "avg_trade": 7.67,
    "final_equity": 9595.54,
    "expectancy_r": 0.1875,
    "avg_r": 0.1875,
    "r_count": 617,
    "edge_p_value": 0.006248,
    "edge_significant": true,
    "var_95_pct": 1.506,
    "cvar_95_pct": 2.383,
    "calmar": 0.5432,
    "mc_p95_drawdown_pct": 26.36,
    "mc_fragile": false,
    "strategy_breakdown": {
      "momentum_breakout": {
        "trades": 102,
        "total_pnl": 2694.72,
        "win_rate_pct": 36.3
      },
      "sector_rotation": {
        "trades": 506,
        "total_pnl": 1884.71,
        "win_rate_pct": 39.7
      },
      "connors_rsi2": {
        "trades": 1,
        "total_pnl": 28.27,
        "win_rate_pct": 100.0
      },
      "mean_reversion": {
        "trades": 8,
        "total_pnl": 126.41,
        "win_rate_pct": 62.5
      }
    },
    "regime_metrics": {
      "bear": {
        "trades": 17,
        "win_rate_pct": 41.2,
        "avg_trade": 14.52,
        "total_pnl": 246.92,
        "profit_factor": 1.892,
        "sharpe_approx": 0.2167,
        "avg_r": 0.4289
      },
      "bull": {
        "trades": 201,
        "win_rate_pct": 37.8,
        "avg_trade": 9.97,
        "total_pnl": 2004.87,
        "profit_factor": 1.4117,
        "sharpe_approx": 0.1274,
        "avg_r": 0.2224
      },
      "neutral": {
        "trades": 399,
        "win_rate_pct": 40.4,
        "avg_trade": 6.22,
        "total_pnl": 2482.32,
        "profit_factor": 1.2177,
        "sharpe_approx": 0.0728,
        "avg_r": 0.1596
      }
    },
    "solo_sharpe": 0.4652,
    "runtime_s": 515.1
  },
  "description": "atr_stop_mult: 1.5 \u2192 1.35",
  "experiments_run": 527,
  "experiments_kept": 29,
  "updated_at": "2026-04-13T11:03:27.735168+00:00"
}