{
  "trade_date": "2026-03-02",
  "generated_at": "2026-03-02T19:03:53.578557",
  "market_id": "asx",
  "config_version": "asx_ibkr_tf_only_v1.0",
  "status": "REJECTED",
  "portfolio_snapshot": {
    "equity": 3999.0,
    "cash": 3999.0,
    "open_positions": 0,
    "total_pnl": 0.0,
    "total_pnl_pct": 0.0
  },
  "proposed_entries": [
    {
      "ticker": "JHX.AX",
      "strategy": "trend_following",
      "entry_price": 34.220001220703125,
      "stop_price": 32.2274,
      "take_profit": null,
      "position_size": 16,
      "position_value": 547.52,
      "risk_amount": 31.88,
      "confidence": 1.0,
      "rationale": "JHX.AX in uptrend (fast MA $35.25 > slow MA $34.18, spread 3.1%). Price pulled back 8.1% from recent high of $37.25 to $34.22. Trend active for 51 bars. Volume 1.7x avg (HIGH). ATR=1.00, stop at $32.23.",
      "features": {
        "fast_ma": 35.254,
        "slow_ma": 34.1838,
        "ma_spread_pct": 3.13,
        "pullback_pct": 8.13,
        "recent_high": 37.25,
        "trend_bars": 51,
        "atr": 0.9963,
        "close": 34.22,
        "volume_ratio": 1.71,
        "breadth_pct_above_50ma": 48.1,
        "breadth_pct_above_200ma": 43.1,
        "breadth_ad_ratio": 1.44,
        "breadth_thrust": 0.0,
        "breadth_momentum": 0.0,
        "breadth_net_new_highs_pct": 3.1,
        "rs_percentile": 75.5,
        "rs_score": 9.04,
        "rs_momentum": 0.0,
        "roc_20": 3.29,
        "roc_60": 14.45,
        "roc_120": 10.67
      },
      "sector": "Unknown",
      "market_id": ""
    },
    {
      "ticker": "REH.AX",
      "strategy": "trend_following",
      "entry_price": 15.65999984741211,
      "stop_price": 14.3954,
      "take_profit": null,
      "position_size": 36,
      "position_value": 563.76,
      "risk_amount": 45.53,
      "confidence": 0.9945,
      "rationale": "REH.AX in uptrend (fast MA $14.99 > slow MA $14.42, spread 3.9%). Price pulled back 5.9% from recent high of $16.64 to $15.66. Trend active for 59 bars. Volume 1.3x avg. ATR=0.63, stop at $14.40.",
      "features": {
        "fast_ma": 14.987,
        "slow_ma": 14.422,
        "ma_spread_pct": 3.92,
        "pullback_pct": 5.89,
        "recent_high": 16.64,
        "trend_bars": 59,
        "atr": 0.6323,
        "close": 15.66,
        "volume_ratio": 1.28,
        "breadth_pct_above_50ma": 48.1,
        "breadth_pct_above_200ma": 43.1,
        "breadth_ad_ratio": 1.44,
        "breadth_thrust": 0.0,
        "breadth_momentum": 0.0,
        "breadth_net_new_highs_pct": 3.1,
        "rs_percentile": 89.9,
        "rs_score": 23.35,
        "rs_momentum": 0.0,
        "roc_20": 5.81,
        "roc_60": 25.68,
        "roc_120": 48.16
      },
      "sector": "Unknown",
      "market_id": ""
    },
    {
      "ticker": "PDN.AX",
      "strategy": "trend_following",
      "entry_price": 13.390000343322754,
      "stop_price": 12.0757,
      "take_profit": null,
      "position_size": 42,
      "position_value": 562.38,
      "risk_amount": 55.2,
      "confidence": 0.9652,
      "rationale": "PDN.AX in uptrend (fast MA $13.10 > slow MA $12.26, spread 6.9%). Price pulled back 5.3% from recent high of $14.14 to $13.39. Trend active for 53 bars. Volume 0.7x avg. ATR=0.66, stop at $12.08.",
      "features": {
        "fast_ma": 13.097,
        "slow_ma": 12.2552,
        "ma_spread_pct": 6.87,
        "pullback_pct": 5.3,
        "recent_high": 14.14,
        "trend_bars": 53,
        "atr": 0.6571,
        "close": 13.39,
        "volume_ratio": 0.71,
        "breadth_pct_above_50ma": 48.1,
        "breadth_pct_above_200ma": 43.1,
        "breadth_ad_ratio": 1.44,
        "breadth_thrust": 0.0,
        "breadth_momentum": 0.0,
        "breadth_net_new_highs_pct": 3.1,
        "rs_percentile": 97.5,
        "rs_score": 38.15,
        "rs_momentum": 0.0,
        "roc_20": -3.25,
        "roc_60": 67.38,
        "roc_120": 63.49
      },
      "sector": "Unknown",
      "market_id": ""
    },
    {
      "ticker": "ADH.AX",
      "strategy": "trend_following",
      "entry_price": 1.8899999856948853,
      "stop_price": 1.7238,
      "take_profit": null,
      "position_size": 301,
      "position_value": 568.89,
      "risk_amount": 50.03,
      "confidence": 0.9464,
      "rationale": "ADH.AX in uptrend (fast MA $1.86 > slow MA $1.83, spread 2.0%). Price pulled back 6.0% from recent high of $2.01 to $1.89. Trend active for 16 bars. Volume 0.8x avg. ATR=0.08, stop at $1.72.",
      "features": {
        "fast_ma": 1.861,
        "slow_ma": 1.8254,
        "ma_spread_pct": 1.95,
        "pullback_pct": 5.97,
        "recent_high": 2.01,
        "trend_bars": 16,
        "atr": 0.0831,
        "close": 1.89,
        "volume_ratio": 0.79,
        "breadth_pct_above_50ma": 48.1,
        "breadth_pct_above_200ma": 43.1,
        "breadth_ad_ratio": 1.44,
        "breadth_thrust": 0.0,
        "breadth_momentum": 0.0,
        "breadth_net_new_highs_pct": 3.1,
        "rs_percentile": 50.3,
        "rs_score": -2.31,
        "rs_momentum": 0.0,
        "roc_20": 8.0,
        "roc_60": 3.56,
        "roc_120": -27.03
      },
      "sector": "Unknown",
      "market_id": ""
    },
    {
      "ticker": "AGL.AX",
      "strategy": "trend_following",
      "entry_price": 9.890000343322754,
      "stop_price": 9.4139,
      "take_profit": null,
      "position_size": 57,
      "position_value": 563.73,
      "risk_amount": 27.14,
      "confidence": 0.92,
      "rationale": "AGL.AX in uptrend (fast MA $10.28 > slow MA $9.38, spread 9.5%). Price pulled back 6.7% from recent high of $10.60 to $9.89. Trend active for 12 bars. Volume 0.8x avg. ATR=0.24, stop at $9.41.",
      "features": {
        "fast_ma": 10.275,
        "slow_ma": 9.3832,
        "ma_spread_pct": 9.5,
        "pullback_pct": 6.7,
        "recent_high": 10.6,
        "trend_bars": 12,
        "atr": 0.2381,
        "close": 9.89,
        "volume_ratio": 0.83,
        "breadth_pct_above_50ma": 48.1,
        "breadth_pct_above_200ma": 43.1,
        "breadth_ad_ratio": 1.44,
        "breadth_thrust": 0.0,
        "breadth_momentum": 0.0,
        "breadth_net_new_highs_pct": 3.1,
        "rs_percentile": 79.2,
        "rs_score": 10.9,
        "rs_momentum": 0.0,
        "roc_20": 9.28,
        "roc_60": 6.12,
        "roc_120": 20.17
      },
      "sector": "Unknown",
      "market_id": ""
    },
    {
      "ticker": "NHC.AX",
      "strategy": "trend_following",
      "entry_price": 4.690000057220459,
      "stop_price": 4.3952,
      "take_profit": null,
      "position_size": 121,
      "position_value": 567.49,
      "risk_amount": 35.67,
      "confidence": 0.9143,
      "rationale": "NHC.AX in uptrend (fast MA $4.75 > slow MA $4.53, spread 4.8%). Price pulled back 4.3% from recent high of $4.90 to $4.69. Trend active for 38 bars. Volume 0.7x avg. ATR=0.15, stop at $4.40.",
      "features": {
        "fast_ma": 4.745,
        "slow_ma": 4.5295,
        "ma_spread_pct": 4.76,
        "pullback_pct": 4.29,
        "recent_high": 4.9,
        "trend_bars": 38,
        "atr": 0.1474,
        "close": 4.69,
        "volume_ratio": 0.7,
        "breadth_pct_above_50ma": 48.1,
        "breadth_pct_above_200ma": 43.1,
        "breadth_ad_ratio": 1.44,
        "breadth_thrust": 0.0,
        "breadth_momentum": 0.0,
        "breadth_net_new_highs_pct": 3.1,
        "rs_percentile": 78.6,
        "rs_score": 10.86,
        "rs_momentum": 0.0,
        "roc_20": 3.99,
        "roc_60": 22.77,
        "roc_120": 5.16
      },
      "sector": "Unknown",
      "market_id": ""
    },
    {
      "ticker": "BGA.AX",
      "strategy": "trend_following",
      "entry_price": 6.28000020980835,
      "stop_price": 5.8827,
      "take_profit": null,
      "position_size": 90,
      "position_value": 565.2,
      "risk_amount": 35.76,
      "confidence": 0.8988,
      "rationale": "BGA.AX in uptrend (fast MA $6.22 > slow MA $6.09, spread 2.1%). Price pulled back 4.0% from recent high of $6.54 to $6.28. Trend active for 21 bars. Volume 2.8x avg (HIGH). ATR=0.20, stop at $5.88.",
      "features": {
        "fast_ma": 6.217,
        "slow_ma": 6.087,
        "ma_spread_pct": 2.14,
        "pullback_pct": 3.98,
        "recent_high": 6.54,
        "trend_bars": 21,
        "atr": 0.1987,
        "close": 6.28,
        "volume_ratio": 2.82,
        "breadth_pct_above_50ma": 48.1,
        "breadth_pct_above_200ma": 43.1,
        "breadth_ad_ratio": 1.44,
        "breadth_thrust": 0.0,
        "breadth_momentum": 0.0,
        "breadth_net_new_highs_pct": 3.1,
        "rs_percentile": 71.1,
        "rs_score": 5.82,
        "rs_momentum": 0.0,
        "roc_20": 2.78,
        "roc_60": 5.19,
        "roc_120": 11.55
      },
      "sector": "Unknown",
      "market_id": ""
    }
  ],
  "rejected_entries": [
    {
      "ticker": "S32.AX",
      "strategy": "trend_following",
      "entry_price": 4.599999904632568,
      "stop_price": 4.3168,
      "take_profit": null,
      "position_size": 123,
      "position_value": 565.8,
      "risk_amount": 34.83,
      "confidence": 0.8983,
      "rationale": "S32.AX in uptrend (fast MA $4.48 > slow MA $4.31, spread 3.8%). Price pulled back 4.0% from recent high of $4.79 to $4.60. Trend active for 59 bars. Volume 1.1x avg. ATR=0.14, stop at $4.32.",
      "features": {
        "fast_ma": 4.477,
        "slow_ma": 4.3137,
        "ma_spread_pct": 3.78,
        "pullback_pct": 3.97,
        "recent_high": 4.79,
        "trend_bars": 59,
        "atr": 0.1416,
        "close": 4.6,
        "volume_ratio": 1.07,
        "breadth_pct_above_50ma": 48.1,
        "breadth_pct_above_200ma": 43.1,
        "breadth_ad_ratio": 1.44,
        "breadth_thrust": 0.0,
        "breadth_momentum": 0.0,
        "breadth_net_new_highs_pct": 3.1,
        "rs_percentile": 96.2,
        "rs_score": 31.86,
        "rs_momentum": 0.0,
        "roc_20": -0.43,
        "roc_60": 38.97,
        "roc_120": 73.58
      },
      "sector": "Unknown",
      "market_id": "",
      "rejection_reason": "Max positions (7) would be exceeded"
    },
    {
      "ticker": "AMC.AX",
      "strategy": "trend_following",
      "entry_price": 67.83999633789062,
      "stop_price": 65.5054,
      "take_profit": null,
      "position_size": 8,
      "position_value": 542.72,
      "risk_amount": 18.68,
      "confidence": 0.8924,
      "rationale": "AMC.AX in uptrend (fast MA $70.03 > slow MA $66.24, spread 5.7%). Price pulled back 4.2% from recent high of $70.85 to $67.84. Trend active for 18 bars. Volume 0.6x avg. ATR=1.17, stop at $65.51.",
      "features": {
        "fast_ma": 70.03,
        "slow_ma": 66.239,
        "ma_spread_pct": 5.72,
        "pullback_pct": 4.25,
        "recent_high": 70.85,
        "trend_bars": 18,
        "atr": 1.1673,
        "close": 67.84,
        "volume_ratio": 0.61,
        "breadth_pct_above_50ma": 48.1,
        "breadth_pct_above_200ma": 43.1,
        "breadth_ad_ratio": 1.44,
        "breadth_thrust": 0.0,
        "breadth_momentum": 0.0,
        "breadth_net_new_highs_pct": 3.1,
        "rs_percentile": 72.3,
        "rs_score": 6.93,
        "rs_momentum": 0.0,
        "roc_20": 8.56,
        "roc_60": 4.53,
        "roc_120": 7.68
      },
      "sector": "Unknown",
      "market_id": "",
      "rejection_reason": "Max positions (7) would be exceeded"
    },
    {
      "ticker": "NXT.AX",
      "strategy": "trend_following",
      "entry_price": 13.880000114440918,
      "stop_price": 12.7431,
      "take_profit": null,
      "position_size": 41,
      "position_value": 569.08,
      "risk_amount": 46.61,
      "confidence": 0.8604,
      "rationale": "NXT.AX in uptrend (fast MA $13.86 > slow MA $13.25, spread 4.6%). Price pulled back 3.2% from recent high of $14.34 to $13.88. Trend active for 23 bars. Volume 1.6x avg (HIGH). ATR=0.57, stop at $12.74.",
      "features": {
        "fast_ma": 13.856,
        "slow_ma": 13.2525,
        "ma_spread_pct": 4.55,
        "pullback_pct": 3.21,
        "recent_high": 14.34,
        "trend_bars": 23,
        "atr": 0.5685,
        "close": 13.88,
        "volume_ratio": 1.58,
        "breadth_pct_above_50ma": 48.1,
        "breadth_pct_above_200ma": 43.1,
        "breadth_ad_ratio": 1.44,
        "breadth_thrust": 0.0,
        "breadth_momentum": 0.0,
        "breadth_net_new_highs_pct": 3.1,
        "rs_percentile": 51.6,
        "rs_score": -1.98,
        "rs_momentum": 0.0,
        "roc_20": 4.2,
        "roc_60": 1.17,
        "roc_120": -16.28
      },
      "sector": "Unknown",
      "market_id": "",
      "rejection_reason": "Max positions (7) would be exceeded"
    },
    {
      "ticker": "SGM.AX",
      "strategy": "trend_following",
      "entry_price": 21.959999084472656,
      "stop_price": 20.4995,
      "take_profit": null,
      "position_size": 25,
      "position_value": 549.0,
      "risk_amount": 36.51,
      "confidence": 0.8545,
      "rationale": "SGM.AX in uptrend (fast MA $21.82 > slow MA $20.40, spread 7.0%). Price pulled back 3.1% from recent high of $22.66 to $21.96. Trend active for 59 bars. Volume 0.8x avg. ATR=0.73, stop at $20.50.",
      "features": {
        "fast_ma": 21.816,
        "slow_ma": 20.3965,
        "ma_spread_pct": 6.96,
        "pullback_pct": 3.09,
        "recent_high": 22.66,
        "trend_bars": 59,
        "atr": 0.7303,
        "close": 21.96,
        "volume_ratio": 0.8,
        "breadth_pct_above_50ma": 48.1,
        "breadth_pct_above_200ma": 43.1,
        "breadth_ad_ratio": 1.44,
        "breadth_thrust": 0.0,
        "breadth_momentum": 0.0,
        "breadth_net_new_highs_pct": 3.1,
        "rs_percentile": 93.1,
        "rs_score": 28.33,
        "rs_momentum": 0.0,
        "roc_20": 8.28,
        "roc_60": 28.65,
        "roc_120": 59.94
      },
      "sector": "Unknown",
      "market_id": "",
      "rejection_reason": "Max positions (7) would be exceeded"
    },
    {
      "ticker": "STO.AX",
      "strategy": "trend_following",
      "entry_price": 6.760000228881836,
      "stop_price": 6.4264,
      "take_profit": null,
      "position_size": 84,
      "position_value": 567.84,
      "risk_amount": 28.02,
      "confidence": 0.8489,
      "rationale": "STO.AX in uptrend (fast MA $6.79 > slow MA $6.57, spread 3.4%). Price pulled back 4.0% from recent high of $7.04 to $6.76. Trend active for 24 bars. Volume 1.2x avg. ATR=0.17, stop at $6.43.",
      "features": {
        "fast_ma": 6.787,
        "slow_ma": 6.5665,
        "ma_spread_pct": 3.36,
        "pullback_pct": 3.98,
        "recent_high": 7.04,
        "trend_bars": 24,
        "atr": 0.1668,
        "close": 6.76,
        "volume_ratio": 1.23,
        "breadth_pct_above_50ma": 48.1,
        "breadth_pct_above_200ma": 43.1,
        "breadth_ad_ratio": 1.44,
        "breadth_thrust": 0.0,
        "breadth_momentum": 0.0,
        "breadth_net_new_highs_pct": 3.1,
        "rs_percentile": 48.4,
        "rs_score": -2.88,
        "rs_momentum": 0.0,
        "roc_20": -3.57,
        "roc_60": 4.64,
        "roc_120": -12.32,
        "rs_confidence_adj": -0.05,
        "rs_confidence_orig": 0.8989
      },
      "sector": "Unknown",
      "market_id": "",
      "rejection_reason": "Max positions (7) would be exceeded"
    },
    {
      "ticker": "BRG.AX",
      "strategy": "trend_following",
      "entry_price": 31.90999984741211,
      "stop_price": 29.2514,
      "take_profit": null,
      "position_size": 17,
      "position_value": 542.47,
      "risk_amount": 45.2,
      "confidence": 0.8337,
      "rationale": "BRG.AX in uptrend (fast MA $31.77 > slow MA $31.35, spread 1.3%). Price pulled back 6.2% from recent high of $34.01 to $31.91. Trend active for 32 bars. Volume 0.6x avg (LOW). ATR=1.33, stop at $29.25.",
      "features": {
        "fast_ma": 31.772,
        "slow_ma": 31.3535,
        "ma_spread_pct": 1.33,
        "pullback_pct": 6.17,
        "recent_high": 34.01,
        "trend_bars": 32,
        "atr": 1.3293,
        "close": 31.91,
        "volume_ratio": 0.58,
        "breadth_pct_above_50ma": 48.1,
        "breadth_pct_above_200ma": 43.1,
        "breadth_ad_ratio": 1.44,
        "breadth_thrust": 0.0,
        "breadth_momentum": 0.0,
        "breadth_net_new_highs_pct": 3.1,
        "rs_percentile": 58.5,
        "rs_score": 1.64,
        "rs_momentum": 0.0,
        "roc_20": -0.9,
        "roc_60": 4.55,
        "roc_120": 1.62
      },
      "sector": "Unknown",
      "market_id": "",
      "rejection_reason": "Max positions (7) would be exceeded"
    },
    {
      "ticker": "QBE.AX",
      "strategy": "trend_following",
      "entry_price": 21.729999542236328,
      "stop_price": 20.5411,
      "take_profit": null,
      "position_size": 26,
      "position_value": 564.98,
      "risk_amount": 30.91,
      "confidence": 0.8125,
      "rationale": "QBE.AX in uptrend (fast MA $21.00 > slow MA $20.11, spread 4.4%). Price pulled back 2.2% from recent high of $22.23 to $21.73. Trend active for 43 bars. Volume 1.9x avg (HIGH). ATR=0.59, stop at $20.54.",
      "features": {
        "fast_ma": 21.004,
        "slow_ma": 20.115,
        "ma_spread_pct": 4.42,
        "pullback_pct": 2.25,
        "recent_high": 22.23,
        "trend_bars": 43,
        "atr": 0.5945,
        "close": 21.73,
        "volume_ratio": 1.85,
        "breadth_pct_above_50ma": 48.1,
        "breadth_pct_above_200ma": 43.1,
        "breadth_ad_ratio": 1.44,
        "breadth_thrust": 0.0,
        "breadth_momentum": 0.0,
        "breadth_net_new_highs_pct": 3.1,
        "rs_percentile": 77.4,
        "rs_score": 9.56,
        "rs_momentum": 0.0,
        "roc_20": 10.08,
        "roc_60": 12.71,
        "roc_120": 4.32
      },
      "sector": "Unknown",
      "market_id": "",
      "rejection_reason": "Max positions (7) would be exceeded"
    },
    {
      "ticker": "ANZ.AX",
      "strategy": "trend_following",
      "entry_price": 40.040000915527344,
      "stop_price": 38.4079,
      "take_profit": null,
      "position_size": 14,
      "position_value": 560.56,
      "risk_amount": 22.85,
      "confidence": 0.8039,
      "rationale": "ANZ.AX in uptrend (fast MA $39.80 > slow MA $37.61, spread 5.8%). Price pulled back 2.1% from recent high of $40.89 to $40.04. Trend active for 45 bars. Volume 1.5x avg (HIGH). ATR=0.82, stop at $38.41.",
      "features": {
        "fast_ma": 39.795,
        "slow_ma": 37.6092,
        "ma_spread_pct": 5.81,
        "pullback_pct": 2.08,
        "recent_high": 40.89,
        "trend_bars": 45,
        "atr": 0.8161,
        "close": 40.04,
        "volume_ratio": 1.51,
        "breadth_pct_above_50ma": 48.1,
        "breadth_pct_above_200ma": 43.1,
        "breadth_ad_ratio": 1.44,
        "breadth_thrust": 0.0,
        "breadth_momentum": 0.0,
        "breadth_net_new_highs_pct": 3.1,
        "rs_percentile": 84.3,
        "rs_score": 15.0,
        "rs_momentum": 0.0,
        "roc_20": 9.1,
        "roc_60": 17.08,
        "roc_120": 21.52
      },
      "sector": "Unknown",
      "market_id": "",
      "rejection_reason": "Max positions (7) would be exceeded"
    },
    {
      "ticker": "MQG.AX",
      "strategy": "trend_following",
      "entry_price": 213.47999572753906,
      "stop_price": 204.1756,
      "take_profit": null,
      "position_size": 3,
      "position_value": 640.44,
      "risk_amount": 27.91,
      "confidence": 0.8013,
      "rationale": "MQG.AX in uptrend (fast MA $214.81 > slow MA $211.53, spread 1.6%). Price pulled back 4.3% from recent high of $223.00 to $213.48. Trend active for 43 bars. Volume 1.4x avg. ATR=4.65, stop at $204.18.",
      "features": {
        "fast_ma": 214.813,
        "slow_ma": 211.5313,
        "ma_spread_pct": 1.55,
        "pullback_pct": 4.27,
        "recent_high": 223.0,
        "trend_bars": 43,
        "atr": 4.6522,
        "close": 213.48,
        "volume_ratio": 1.42,
        "breadth_pct_above_50ma": 48.1,
        "breadth_pct_above_200ma": 43.1,
        "breadth_ad_ratio": 1.44,
        "breadth_thrust": 0.0,
        "breadth_momentum": 0.0,
        "breadth_net_new_highs_pct": 3.1,
        "rs_percentile": 62.3,
        "rs_score": 2.46,
        "rs_momentum": 0.0,
        "roc_20": 0.61,
        "roc_60": 8.8,
        "roc_120": -3.47
      },
      "sector": "Unknown",
      "market_id": "",
      "rejection_reason": "Max positions (7) would be exceeded"
    },
    {
      "ticker": "BGL.AX",
      "strategy": "trend_following",
      "entry_price": 1.8250000476837158,
      "stop_price": 1.6415,
      "take_profit": null,
      "position_size": 312,
      "position_value": 569.4,
      "risk_amount": 57.25,
      "confidence": 0.7899,
      "rationale": "BGL.AX in uptrend (fast MA $1.79 > slow MA $1.77, spread 1.2%). Price pulled back 8.3% from recent high of $1.99 to $1.83. Trend active for 59 bars. Volume 1.6x avg (HIGH). ATR=0.09, stop at $1.64.",
      "features": {
        "fast_ma": 1.7885,
        "slow_ma": 1.768,
        "ma_spread_pct": 1.16,
        "pullback_pct": 8.29,
        "recent_high": 1.99,
        "trend_bars": 59,
        "atr": 0.0917,
        "close": 1.825,
        "volume_ratio": 1.6,
        "breadth_pct_above_50ma": 48.1,
        "breadth_pct_above_200ma": 43.1,
        "breadth_ad_ratio": 1.44,
        "breadth_thrust": 0.0,
        "breadth_momentum": 0.0,
        "breadth_net_new_highs_pct": 3.1,
        "rs_percentile": 96.9,
        "rs_score": 37.16,
        "rs_momentum": 0.0,
        "roc_20": -3.18,
        "roc_60": 38.78,
        "roc_120": 99.45
      },
      "sector": "Unknown",
      "market_id": "",
      "rejection_reason": "Max positions (7) would be exceeded"
    },
    {
      "ticker": "CBA.AX",
      "strategy": "trend_following",
      "entry_price": 174.6199951171875,
      "stop_price": 167.6792,
      "take_profit": null,
      "position_size": 3,
      "position_value": 523.86,
      "risk_amount": 20.82,
      "confidence": 0.7705,
      "rationale": "CBA.AX in uptrend (fast MA $177.86 > slow MA $161.45, spread 10.2%). Price pulled back 2.8% from recent high of $179.67 to $174.62. Trend active for 13 bars. Volume 1.8x avg (HIGH). ATR=3.47, stop at $167.68.",
      "features": {
        "fast_ma": 177.865,
        "slow_ma": 161.4503,
        "ma_spread_pct": 10.17,
        "pullback_pct": 2.81,
        "recent_high": 179.67,
        "trend_bars": 13,
        "atr": 3.4704,
        "close": 174.62,
        "volume_ratio": 1.77,
        "breadth_pct_above_50ma": 48.1,
        "breadth_pct_above_200ma": 43.1,
        "breadth_ad_ratio": 1.44,
        "breadth_thrust": 0.0,
        "breadth_momentum": 0.0,
        "breadth_net_new_highs_pct": 3.1,
        "rs_percentile": 82.4,
        "rs_score": 13.02,
        "rs_momentum": 0.0,
        "roc_20": 16.91,
        "roc_60": 15.15,
        "roc_120": 3.79
      },
      "sector": "Unknown",
      "market_id": "",
      "rejection_reason": "Max positions (7) would be exceeded"
    },
    {
      "ticker": "SFR.AX",
      "strategy": "trend_following",
      "entry_price": 20.190000534057617,
      "stop_price": 18.8212,
      "take_profit": null,
      "position_size": 28,
      "position_value": 565.32,
      "risk_amount": 38.33,
      "confidence": 0.7519,
      "rationale": "SFR.AX in uptrend (fast MA $19.53 > slow MA $19.31, spread 1.2%). Price pulled back 5.3% from recent high of $21.31 to $20.19. Trend active for 57 bars. Volume 0.8x avg. ATR=0.68, stop at $18.82.",
      "features": {
        "fast_ma": 19.531,
        "slow_ma": 19.3078,
        "ma_spread_pct": 1.16,
        "pullback_pct": 5.26,
        "recent_high": 21.31,
        "trend_bars": 57,
        "atr": 0.6844,
        "close": 20.19,
        "volume_ratio": 0.84,
        "breadth_pct_above_50ma": 48.1,
        "breadth_pct_above_200ma": 43.1,
        "breadth_ad_ratio": 1.44,
        "breadth_thrust": 0.0,
        "breadth_momentum": 0.0,
        "breadth_net_new_highs_pct": 3.1,
        "rs_percentile": 91.8,
        "rs_score": 26.05,
        "rs_momentum": 0.0,
        "roc_20": 1.71,
        "roc_60": 26.66,
        "roc_120": 64.15
      },
      "sector": "Unknown",
      "market_id": "",
      "rejection_reason": "Max positions (7) would be exceeded"
    }
  ],
  "proposed_exits": [],
  "total_signals_generated": 19,
  "risk_summary": {
    "total_proposed_cost": 3938.97,
    "total_proposed_risk": 281.21,
    "risk_pct_of_equity": 7.03,
    "positions_after": 7,
    "cash_after_entries": 60.03,
    "portfolio_exposure_pct": 98.5
  },
  "open_positions": [],
  "rejected_at": "2026-03-03T01:24:54.035832"
}