{
  "pass": false,
  "reason": "OOS Sharpe -0.1646 \u2264 0",
  "sharpe_oos": -0.1646,
  "profit_factor_oos": 5.5915,
  "cagr_degradation_pct": -622.9,
  "perturbation_pass_rate": 0.9,
  "raw": {
    "test1_verdict": "FAIL - significant OOS degradation",
    "test2_verdict": "PASS",
    "test3_verdict": "FAIL - inconsistent windows",
    "overall_verdict": "MIXED - review individual tests",
    "total_runtime_s": 68.1,
    "total_runtime_min": 1.1
  },
  "cached_at": "2026-05-05T14:09:44.887134+00:00"
}